app/__init__.py
app/taskwizard.py
app/src/__init__.py
app/src/models.py
app/src/taskwizard_db.py
app/src/text_helpers.py
app/src/cmd/TaskWizardCLI.py
app/src/cmd/__init__.py
app/src/cmd/cmd_actions.py
taskwizard-1.0.1.dist-info/LICENSE
taskwizard-1.0.1.dist-info/METADATA
taskwizard-1.0.1.dist-info/WHEEL
taskwizard-1.0.1.dist-info/entry_points.txt
taskwizard-1.0.1.dist-info/top_level.txt
taskwizard-1.0.1.dist-info/RECORD
