Metadata-Version: 2.1
Name: taskwizard
Version: 1.0.1
Summary: A CLI task management system
Home-page: https://github.com/srgeddes/taskwizard.git
Author: Riley Geddes
License: MIT
Classifier: License :: OSI Approved :: MIT License
Classifier: Programming Language :: Python :: 3.10
Classifier: Operating System :: OS Independent
License-File: LICENSE
Requires-Dist: click
